marvin_python_toolbox/VERSION
marvin_python_toolbox/__init__.py
marvin_python_toolbox/_compatibility.py
marvin_python_toolbox/_logging.py
marvin_python_toolbox/config.py
marvin_python_toolbox/decorators.py
marvin_python_toolbox/loader.py
marvin_python_toolbox/manage.py
marvin_python_toolbox/common/__init__.py
marvin_python_toolbox/common/config.py
marvin_python_toolbox/common/data.py
marvin_python_toolbox/common/data_source_provider.py
marvin_python_toolbox/common/exceptions.py
marvin_python_toolbox/common/http_client.py
marvin_python_toolbox/common/profiling.py
marvin_python_toolbox/common/utils.py
marvin_python_toolbox/engine_base/__init__.py
marvin_python_toolbox/engine_base/engine_base_action.py
marvin_python_toolbox/engine_base/engine_base_data_handler.py
marvin_python_toolbox/engine_base/engine_base_prediction.py
marvin_python_toolbox/engine_base/engine_base_training.py
marvin_python_toolbox/engine_base/serializers/__init__.py
marvin_python_toolbox/engine_base/serializers/keras_serializer.py
marvin_python_toolbox/engine_base/stubs/__init__.py
marvin_python_toolbox/engine_base/stubs/actions_pb2.py
marvin_python_toolbox/engine_base/stubs/actions_pb2_grpc.py
marvin_python_toolbox/extras/marvin_bash_completion
marvin_python_toolbox/extras/notebook_extensions/jupyter_notebook_config.py
marvin_python_toolbox/extras/notebook_extensions/main.js
marvin_python_toolbox/management/__init__.py
marvin_python_toolbox/management/engine.py
marvin_python_toolbox/management/hive.py
marvin_python_toolbox/management/notebook.py
marvin_python_toolbox/management/pkg.py
marvin_python_toolbox/management/test.py
marvin_python_toolbox/management/templates/python-engine/.bumpversion.cfg
marvin_python_toolbox/management/templates/python-engine/.coveragerc
marvin_python_toolbox/management/templates/python-engine/.gitignore
marvin_python_toolbox/management/templates/python-engine/CHANGES.md
marvin_python_toolbox/management/templates/python-engine/Dockerfile
marvin_python_toolbox-0.0.5.dist-info/METADATA
marvin_python_toolbox-0.0.5.dist-info/NOTICE
marvin_python_toolbox-0.0.5.dist-info/WHEEL
marvin_python_toolbox-0.0.5.dist-info/top_level.txt
marvin_python_toolbox-0.0.5.dist-info/RECORD
