Metadata-Version: 2.1
Name: marvin-python-toolbox
Version: 0.0.5
Summary: Marvin Python Toolbox
Home-page: https://github.com/marvin-ai/marvin-python-toolbox
Author: Daniel Takabayashi
Maintainer: Daniel Takabayashi
Maintainer-email: daniel.takabayashi@gmail.com
License: UNKNOWN
Platform: UNKNOWN
Classifier: Development Status :: 5 - Production/Stable
Classifier: Programming Language :: Python :: 2
Classifier: Programming Language :: Python :: 2.7
Classifier: Programming Language :: Python :: 3
Classifier: Programming Language :: Python :: 3.6
Requires-Dist: six (>=1.10.0)
Requires-Dist: bumpversion (>=0.5.3)
Requires-Dist: click (>=3.3)
Requires-Dist: jupyter (>=1.0.0)
Requires-Dist: jupyterlab (>=0.32.1)
Requires-Dist: pep8 (>=1.7.0)
Requires-Dist: virtualenv (>=15.0.1)
Requires-Dist: jsonschema (>=2.5.1)
Requires-Dist: python-slugify (>=0.1.0)
Requires-Dist: paramiko (>=2.1.2)
Requires-Dist: PyHive (>=0.3.0)
Requires-Dist: thrift (>=0.10.0)
Requires-Dist: thrift-sasl (>=0.2.1)
Requires-Dist: virtualenvwrapper (>=4.7.1)
Requires-Dist: requests (>=2.19.1)
Requires-Dist: python-dateutil (>=2.7.3)
Requires-Dist: path.py (>=7.2)
Requires-Dist: httpretty (>=0.9.5)
Requires-Dist: tornado (>=4.5.3)
Requires-Dist: gprof2dot
Requires-Dist: ujsonpath (>=0.0.2)
Requires-Dist: simplejson (>=3.10.0)
Requires-Dist: configobj (>=5.0.6)
Requires-Dist: findspark (>=1.1.0)
Requires-Dist: grpcio (>=1.13.0)
Requires-Dist: grpcio-tools (>=1.13.0)
Requires-Dist: joblib (>=0.11)
Requires-Dist: autopep8 (>=1.3.3)
Requires-Dist: progressbar2 (>=3.34.3)
Requires-Dist: urllib3 (>=1.21.1)
Requires-Dist: idna (>=2.5)
Requires-Dist: bleach (>=1.5.0)
Requires-Dist: numpy (>=1.16.2)
Requires-Dist: Unidecode (==1.0.23)
Provides-Extra: testing
Requires-Dist: tox (>=2.2.0) ; extra == 'testing'
Requires-Dist: mock (>=2.0.0) ; extra == 'testing'
Requires-Dist: pytest (>=2.9.2) ; extra == 'testing'
Requires-Dist: pytest-cov (<2.6,>=1.8.1) ; extra == 'testing'
Requires-Dist: pytest-watch (>=4.1.0) ; extra == 'testing'
Requires-Dist: pytest-testmon (>=0.8.2) ; extra == 'testing'
Requires-Dist: Keras (>=2.2.0) ; extra == 'testing'
Requires-Dist: tensorflow (>=1.8.0) ; extra == 'testing'
